Metadata-Version: 2.1
Name: clip-anytorch
Version: 2.6.0
Summary: # CLIP
Home-page: https://github.com/rom1504/CLIP
Author: OpenAI
License: UNKNOWN
Platform: UNKNOWN
Provides-Extra: dev
